README.md
setup.cfg
setup.py
cosmos_doc_manager.egg-info/PKG-INFO
cosmos_doc_manager.egg-info/SOURCES.txt
cosmos_doc_manager.egg-info/dependency_links.txt
cosmos_doc_manager.egg-info/entry_points.txt
cosmos_doc_manager.egg-info/requires.txt
cosmos_doc_manager.egg-info/top_level.txt
mongo_connector/__init__.py
mongo_connector/doc_managers/__init__.py
mongo_connector/doc_managers/cosmos_bulk_upsert.py
mongo_connector/doc_managers/cosmos_doc_manager.py
mongo_connector/doc_managers/cosmos_partial_update.py
mongo_connector/doc_managers/cosmos_repository.py
mongo_connector/doc_managers/cosmos_sql_handler.py