Metadata-Version: 1.1
Name: cosmos-doc-manager
Version: 0.0.1
Summary: Azure Cosmos DB Doc Manager for Mongo Connector
Home-page: https://github.com/syedhassaanahmed/cosmos_doc_manager.git
Author: Syed Hassaan Ahmed
Author-email: hassaan.brix@gmail.com
License: MIT License
Platform: UNKNOWN
Classifier: License :: OSI Approved :: MIT License
Classifier: Intended Audience :: Developers
Classifier: Natural Language :: English
Classifier: Operating System :: OS Independent
Classifier: Programming Language :: Python :: 2.7
Classifier: Programming Language :: Python :: 3.3
Classifier: Programming Language :: Python :: 3.4
Classifier: Programming Language :: Python :: 3.5
Classifier: Programming Language :: Python :: 3.6
Classifier: Topic :: Database
Classifier: Topic :: Software Development
